toorajd/__init__.py
toorajd/_plot.py
toorajd/manhattan.py
toorajd-0.1.3.dist-info/METADATA
toorajd-0.1.3.dist-info/WHEEL
toorajd-0.1.3.dist-info/entry_points.txt
toorajd-0.1.3.dist-info/RECORD
